watchmagic/__init__.py
watchmagic/watch.py
watchmagic-0.1.1.dist-info/LICENSE
watchmagic-0.1.1.dist-info/METADATA
watchmagic-0.1.1.dist-info/WHEEL
watchmagic-0.1.1.dist-info/top_level.txt
watchmagic-0.1.1.dist-info/RECORD
