Metadata-Version: 2.1
Name: watchmagic
Version: 0.1.1
Summary: Add watchdog to IPython cells
Home-page: https://github.com/gunnarvoet/watchmagic
Author: Gunnar Voet
Author-email: gvoet@ucsd.edu
License: GNU GPL v3
Project-URL: Documentation, https://github.com/gunnarvoet/watchmagic
Platform: any
Classifier: Development Status :: 3 - Alpha
Classifier: Framework :: IPython
Classifier: License :: OSI Approved :: GNU General Public License v3 (GPLv3)
Classifier: Natural Language :: English
Classifier: Topic :: Software Development
Classifier: Programming Language :: Python :: 3
Classifier: Programming Language :: Python :: 3 :: Only
Requires-Python: >=3.0
Requires-Dist: watchdog
Requires-Dist: IPython
